devops_microsoft_sspo_real_time/__init__.py
devops_microsoft_sspo_real_time/atomic_user_story.py
devops_microsoft_sspo_real_time/base_entity.py
devops_microsoft_sspo_real_time/epic.py
devops_microsoft_sspo_real_time/factories.py
devops_microsoft_sspo_real_time/scrum_development_task.py
devops_microsoft_sspo_real_time/scrum_project.py
devops_microsoft_sspo_real_time/sprint.py
devops_microsoft_sspo_real_time/team_member.py
devops_microsoft_sspo_real_time-4.4.6.dist-info/METADATA
devops_microsoft_sspo_real_time-4.4.6.dist-info/WHEEL
devops_microsoft_sspo_real_time-4.4.6.dist-info/top_level.txt
devops_microsoft_sspo_real_time-4.4.6.dist-info/RECORD
